{"type":"FeatureCollection", "features": [
{"type":"Feature","geometry":null,"properties":{"KEY_CODE":"063240010","PREF":"06","CITY":"324","S_AREA":"001000","PREF_NAME":"山形県","CITY_NAME":"大江町","S_NAME":"大字左沢","KIGO_E":"E6","HCODE":8101,"AREA":2948.272,"PERIMETER":205.664,"R2KAxx":3373,"R2KAxx_ID":3372,"KIHON1":"0010","DUMMY1":"-","KIHON2":"00","KEYCODE1":"324001000","KEYCODE2":"3240010","AREA_MAX_F":"","KIGO_D":"D","N_KEN":"06","N_CITY":"206","KIGO_I":"","KBSUM":0,"JINKO":0,"SETAI":0,"X_CODE":140.233166,"Y_CODE":38.38041,"KCODE1":"0010-00"}},
{"type":"Feature","geometry":null,"properties":{"KEY_CODE":"063240010","PREF":"06","CITY":"324","S_AREA":"001000","PREF_NAME":"山形県","CITY_NAME":"大江町","S_NAME":"大字左沢","KIGO_E":"E9","HCODE":8101,"AREA":9092.277,"PERIMETER":568.902,"R2KAxx":3370,"R2KAxx_ID":3369,"KIHON1":"0010","DUMMY1":"-","KIHON2":"00","KEYCODE1":"324001000","KEYCODE2":"3240010","AREA_MAX_F":"","KIGO_D":"D","N_KEN":"06","N_CITY":"206","KIGO_I":"","KBSUM":0,"JINKO":0,"SETAI":0,"X_CODE":140.232986,"Y_CODE":38.377436,"KCODE1":"0010-00"}},
{"type":"Feature","geometry":null,"properties":{"KEY_CODE":"063240010","PREF":"06","CITY":"324","S_AREA":"001000","PREF_NAME":"山形県","CITY_NAME":"大江町","S_NAME":"大字左沢","KIGO_E":"E8","HCODE":8101,"AREA":85303.986,"PERIMETER":2535.187,"R2KAxx":3369,"R2KAxx_ID":3368,"KIHON1":"0010","DUMMY1":"-","KIHON2":"00","KEYCODE1":"324001000","KEYCODE2":"3240010","AREA_MAX_F":"","KIGO_D":"D","N_KEN":"06","N_CITY":"206","KIGO_I":"","KBSUM":0,"JINKO":0,"SETAI":0,"X_CODE":140.227247,"Y_CODE":38.373838,"KCODE1":"0010-00"}},
{"type":"Feature","geometry":null,"properties":{"KEY_CODE":"063240010","PREF":"06","CITY":"324","S_AREA":"001000","PREF_NAME":"山形県","CITY_NAME":"大江町","S_NAME":"大字左沢","KIGO_E":"E10","HCODE":8101,"AREA":5227.998,"PERIMETER":299.957,"R2KAxx":3368,"R2KAxx_ID":3367,"KIHON1":"0010","DUMMY1":"-","KIHON2":"00","KEYCODE1":"324001000","KEYCODE2":"3240010","AREA_MAX_F":"","KIGO_D":"D","N_KEN":"06","N_CITY":"206","KIGO_I":"","KBSUM":0,"JINKO":0,"SETAI":0,"X_CODE":140.231349,"Y_CODE":38.375941,"KCODE1":"0010-00"}},
{"type":"Feature","geometry":null,"properties":{"KEY_CODE":"063240010","PREF":"06","CITY":"324","S_AREA":"001000","PREF_NAME":"山形県","CITY_NAME":"大江町","S_NAME":"大字左沢","KIGO_E":"E5","HCODE":8101,"AREA":126836.612,"PERIMETER":3284.486,"R2KAxx":3372,"R2KAxx_ID":3371,"KIHON1":"0010","DUMMY1":"-","KIHON2":"00","KEYCODE1":"324001000","KEYCODE2":"3240010","AREA_MAX_F":"","KIGO_D":"D","N_KEN":"06","N_CITY":"206","KIGO_I":"","KBSUM":0,"JINKO":0,"SETAI":0,"X_CODE":140.227702,"Y_CODE":38.377984,"KCODE1":"0010-00"}},
{"type":"Feature","geometry":null,"properties":{"KEY_CODE":"063240010","PREF":"06","CITY":"324","S_AREA":"001000","PREF_NAME":"山形県","CITY_NAME":"大江町","S_NAME":"大字左沢","KIGO_E":"E3","HCODE":8101,"AREA":20953.755,"PERIMETER":640.128,"R2KAxx":3371,"R2KAxx_ID":3370,"KIHON1":"0010","DUMMY1":"-","KIHON2":"00","KEYCODE1":"324001000","KEYCODE2":"3240010","AREA_MAX_F":"","KIGO_D":"D","N_KEN":"06","N_CITY":"206","KIGO_I":"","KBSUM":0,"JINKO":0,"SETAI":0,"X_CODE":140.230834,"Y_CODE":38.379454,"KCODE1":"0010-00"}},
{"type":"Feature","geometry":null,"properties":{"KEY_CODE":"063240010","PREF":"06","CITY":"324","S_AREA":"001000","PREF_NAME":"山形県","CITY_NAME":"大江町","S_NAME":"大字左沢","KIGO_E":"E1","HCODE":8101,"AREA":2517142.107,"PERIMETER":8361.33,"R2KAxx":3377,"R2KAxx_ID":3376,"KIHON1":"0010","DUMMY1":"-","KIHON2":"00","KEYCODE1":"324001000","KEYCODE2":"3240010","AREA_MAX_F":"M","KIGO_D":"","N_KEN":"","N_CITY":"","KIGO_I":"","KBSUM":53,"JINKO":2364,"SETAI":739,"X_CODE":140.207076,"Y_CODE":38.384976,"KCODE1":"0010-00"}},
{"type":"Feature","geometry":null,"properties":{"KEY_CODE":"063240010","PREF":"06","CITY":"324","S_AREA":"001000","PREF_NAME":"山形県","CITY_NAME":"大江町","S_NAME":"大字左沢","KIGO_E":"E2","HCODE":8101,"AREA":523608.353,"PERIMETER":8474.338,"R2KAxx":3376,"R2KAxx_ID":3375,"KIHON1":"0010","DUMMY1":"-","KIHON2":"00","KEYCODE1":"324001000","KEYCODE2":"3240010","AREA_MAX_F":"","KIGO_D":"D","N_KEN":"06","N_CITY":"206","KIGO_I":"","KBSUM":0,"JINKO":0,"SETAI":0,"X_CODE":140.239621,"Y_CODE":38.379243,"KCODE1":"0010-00"}},
{"type":"Feature","geometry":null,"properties":{"KEY_CODE":"063240010","PREF":"06","CITY":"324","S_AREA":"001000","PREF_NAME":"山形県","CITY_NAME":"大江町","S_NAME":"大字左沢","KIGO_E":"E7","HCODE":8101,"AREA":40993.263,"PERIMETER":1925.16,"R2KAxx":3375,"R2KAxx_ID":3374,"KIHON1":"0010","DUMMY1":"-","KIHON2":"00","KEYCODE1":"324001000","KEYCODE2":"3240010","AREA_MAX_F":"","KIGO_D":"D","N_KEN":"06","N_CITY":"206","KIGO_I":"","KBSUM":0,"JINKO":0,"SETAI":0,"X_CODE":140.220715,"Y_CODE":38.379227,"KCODE1":"0010-00"}},
{"type":"Feature","geometry":null,"properties":{"KEY_CODE":"063240010","PREF":"06","CITY":"324","S_AREA":"001000","PREF_NAME":"山形県","CITY_NAME":"大江町","S_NAME":"大字左沢","KIGO_E":"E4","HCODE":8101,"AREA":2849.703,"PERIMETER":260.715,"R2KAxx":3367,"R2KAxx_ID":3366,"KIHON1":"0010","DUMMY1":"-","KIHON2":"00","KEYCODE1":"324001000","KEYCODE2":"3240010","AREA_MAX_F":"","KIGO_D":"D","N_KEN":"06","N_CITY":"206","KIGO_I":"","KBSUM":0,"JINKO":0,"SETAI":0,"X_CODE":140.239857,"Y_CODE":38.370759,"KCODE1":"0010-00"}},
{"type":"Feature","geometry":null,"properties":{"KEY_CODE":"063240010","PREF":"06","CITY":"324","S_AREA":"001000","PREF_NAME":"山形県","CITY_NAME":"大江町","S_NAME":"大字左沢","KIGO_E":"E11","HCODE":8101,"AREA":1750.494,"PERIMETER":189.655,"R2KAxx":3374,"R2KAxx_ID":3373,"KIHON1":"0010","DUMMY1":"-","KIHON2":"00","KEYCODE1":"324001000","KEYCODE2":"3240010","AREA_MAX_F":"","KIGO_D":"D","N_KEN":"06","N_CITY":"206","KIGO_I":"","KBSUM":0,"JINKO":0,"SETAI":0,"X_CODE":140.223176,"Y_CODE":38.380691,"KCODE1":"0010-00"}},
{"type":"Feature","geometry":null,"properties":{"KEY_CODE":"063240020","PREF":"06","CITY":"324","S_AREA":"002000","PREF_NAME":"山形県","CITY_NAME":"大江町","S_NAME":"大字藤田","KIGO_E":"","HCODE":8101,"AREA":1197627.972,"PERIMETER":5320.037,"R2KAxx":3378,"R2KAxx_ID":3377,"KIHON1":"0020","DUMMY1":"-","KIHON2":"00","KEYCODE1":"324002000","KEYCODE2":"3240020","AREA_MAX_F":"M","KIGO_D":"","N_KEN":"","N_CITY":"","KIGO_I":"","KBSUM":15,"JINKO":1224,"SETAI":436,"X_CODE":140.209176,"Y_CODE":38.368634,"KCODE1":"0020-00"}},
{"type":"Feature","geometry":null,"properties":{"KEY_CODE":"063240030","PREF":"06","CITY":"324","S_AREA":"003000","PREF_NAME":"山形県","CITY_NAME":"大江町","S_NAME":"大字小見","KIGO_E":"","HCODE":8101,"AREA":2066160.761,"PERIMETER":7247.87,"R2KAxx":3379,"R2KAxx_ID":3378,"KIHON1":"0030","DUMMY1":"-","KIHON2":"00","KEYCODE1":"324003000","KEYCODE2":"3240030","AREA_MAX_F":"M","KIGO_D":"","N_KEN":"","N_CITY":"","KIGO_I":"","KBSUM":6,"JINKO":453,"SETAI":169,"X_CODE":140.195392,"Y_CODE":38.365732,"KCODE1":"0030-00"}},
{"type":"Feature","geometry":null,"properties":{"KEY_CODE":"063240040","PREF":"06","CITY":"324","S_AREA":"004000","PREF_NAME":"山形県","CITY_NAME":"大江町","S_NAME":"大字富沢","KIGO_E":"","HCODE":8101,"AREA":2191232.371,"PERIMETER":8059.524,"R2KAxx":3380,"R2KAxx_ID":3379,"KIHON1":"0040","DUMMY1":"-","KIHON2":"00","KEYCODE1":"324004000","KEYCODE2":"3240040","AREA_MAX_F":"M","KIGO_D":"","N_KEN":"","N_CITY":"","KIGO_I":"","KBSUM":2,"JINKO":180,"SETAI":50,"X_CODE":140.195118,"Y_CODE":38.356604,"KCODE1":"0040-00"}},
{"type":"Feature","geometry":null,"properties":{"KEY_CODE":"063240050","PREF":"06","CITY":"324","S_AREA":"005000","PREF_NAME":"山形県","CITY_NAME":"大江町","S_NAME":"大字三郷丙","KIGO_E":"E1","HCODE":8101,"AREA":2202697.144,"PERIMETER":6819.643,"R2KAxx":3382,"R2KAxx_ID":3381,"KIHON1":"0050","DUMMY1":"-","KIHON2":"00","KEYCODE1":"324005000","KEYCODE2":"3240050","AREA_MAX_F":"M","KIGO_D":"","N_KEN":"","N_CITY":"","KIGO_I":"","KBSUM":4,"JINKO":174,"SETAI":63,"X_CODE":140.217077,"Y_CODE":38.357098,"KCODE1":"0050-00"}},
{"type":"Feature","geometry":null,"properties":{"KEY_CODE":"063240050","PREF":"06","CITY":"324","S_AREA":"005000","PREF_NAME":"山形県","CITY_NAME":"大江町","S_NAME":"大字三郷丙","KIGO_E":"E2","HCODE":8101,"AREA":11352.764,"PERIMETER":426.306,"R2KAxx":3381,"R2KAxx_ID":3380,"KIHON1":"0050","DUMMY1":"-","KIHON2":"00","KEYCODE1":"324005000","KEYCODE2":"3240050","AREA_MAX_F":"","KIGO_D":"D","N_KEN":"06","N_CITY":"302","KIGO_I":"","KBSUM":0,"JINKO":0,"SETAI":0,"X_CODE":140.262468,"Y_CODE":38.354004,"KCODE1":"0050-00"}},
{"type":"Feature","geometry":null,"properties":{"KEY_CODE":"063240060","PREF":"06","CITY":"324","S_AREA":"006000","PREF_NAME":"山形県","CITY_NAME":"大江町","S_NAME":"大字三郷乙","KIGO_E":"E1","HCODE":8101,"AREA":4951196.166,"PERIMETER":11280.501,"R2KAxx":3383,"R2KAxx_ID":3382,"KIHON1":"0060","DUMMY1":"-","KIHON2":"00","KEYCODE1":"324006000","KEYCODE2":"3240060","AREA_MAX_F":"M","KIGO_D":"","N_KEN":"","N_CITY":"","KIGO_I":"","KBSUM":7,"JINKO":234,"SETAI":77,"X_CODE":140.206805,"Y_CODE":38.341982,"KCODE1":"0060-00"}},
{"type":"Feature","geometry":null,"properties":{"KEY_CODE":"063240060","PREF":"06","CITY":"324","S_AREA":"006000","PREF_NAME":"山形県","CITY_NAME":"大江町","S_NAME":"大字三郷乙","KIGO_E":"E3","HCODE":8101,"AREA":14979.153,"PERIMETER":823.159,"R2KAxx":3385,"R2KAxx_ID":3384,"KIHON1":"0060","DUMMY1":"-","KIHON2":"00","KEYCODE1":"324006000","KEYCODE2":"3240060","AREA_MAX_F":"","KIGO_D":"D","N_KEN":"06","N_CITY":"302","KIGO_I":"","KBSUM":0,"JINKO":0,"SETAI":0,"X_CODE":140.268269,"Y_CODE":38.356577,"KCODE1":"0060-00"}},
{"type":"Feature","geometry":null,"properties":{"KEY_CODE":"063240060","PREF":"06","CITY":"324","S_AREA":"006000","PREF_NAME":"山形県","CITY_NAME":"大江町","S_NAME":"大字三郷乙","KIGO_E":"E2","HCODE":8101,"AREA":18571.548,"PERIMETER":766.312,"R2KAxx":3384,"R2KAxx_ID":3383,"KIHON1":"0060","DUMMY1":"-","KIHON2":"00","KEYCODE1":"324006000","KEYCODE2":"3240060","AREA_MAX_F":"","KIGO_D":"D","N_KEN":"06","N_CITY":"302","KIGO_I":"","KBSUM":0,"JINKO":0,"SETAI":0,"X_CODE":140.269011,"Y_CODE":38.354982,"KCODE1":"0060-00"}},
{"type":"Feature","geometry":null,"properties":{"KEY_CODE":"063240070","PREF":"06","CITY":"324","S_AREA":"007000","PREF_NAME":"山形県","CITY_NAME":"大江町","S_NAME":"大字三郷甲","KIGO_E":"","HCODE":8101,"AREA":1897648.49,"PERIMETER":6689.874,"R2KAxx":3386,"R2KAxx_ID":3385,"KIHON1":"0070","DUMMY1":"-","KIHON2":"00","KEYCODE1":"324007000","KEYCODE2":"3240070","AREA_MAX_F":"M","KIGO_D":"","N_KEN":"","N_CITY":"","KIGO_I":"","KBSUM":1,"JINKO":50,"SETAI":18,"X_CODE":140.193231,"Y_CODE":38.331793,"KCODE1":"0070-00"}},
{"type":"Feature","geometry":null,"properties":{"KEY_CODE":"063240080","PREF":"06","CITY":"324","S_AREA":"008000","PREF_NAME":"山形県","CITY_NAME":"大江町","S_NAME":"大字楢山","KIGO_E":"","HCODE":8101,"AREA":5338038.709,"PERIMETER":10384.124,"R2KAxx":3387,"R2KAxx_ID":3386,"KIHON1":"0080","DUMMY1":"-","KIHON2":"00","KEYCODE1":"324008000","KEYCODE2":"3240080","AREA_MAX_F":"M","KIGO_D":"","N_KEN":"","N_CITY":"","KIGO_I":"","KBSUM":1,"JINKO":52,"SETAI":20,"X_CODE":140.112927,"Y_CODE":38.396269,"KCODE1":"0080-00"}},
{"type":"Feature","geometry":null,"properties":{"KEY_CODE":"063240090","PREF":"06","CITY":"324","S_AREA":"009000","PREF_NAME":"山形県","CITY_NAME":"大江町","S_NAME":"大字月布","KIGO_E":"","HCODE":8101,"AREA":2922669.562,"PERIMETER":6852.739,"R2KAxx":3388,"R2KAxx_ID":3387,"KIHON1":"0090","DUMMY1":"-","KIHON2":"00","KEYCODE1":"324009000","KEYCODE2":"3240090","AREA_MAX_F":"M","KIGO_D":"","N_KEN":"","N_CITY":"","KIGO_I":"","KBSUM":4,"JINKO":88,"SETAI":33,"X_CODE":140.109317,"Y_CODE":38.381567,"KCODE1":"0090-00"}},
{"type":"Feature","geometry":null,"properties":{"KEY_CODE":"063240100","PREF":"06","CITY":"324","S_AREA":"010000","PREF_NAME":"山形県","CITY_NAME":"大江町","S_NAME":"大字十八才","KIGO_E":"","HCODE":8101,"AREA":1711892.371,"PERIMETER":6210.022,"R2KAxx":3389,"R2KAxx_ID":3388,"KIHON1":"0100","DUMMY1":"-","KIHON2":"00","KEYCODE1":"324010000","KEYCODE2":"3240100","AREA_MAX_F":"M","KIGO_D":"","N_KEN":"","N_CITY":"","KIGO_I":"","KBSUM":2,"JINKO":49,"SETAI":21,"X_CODE":140.130375,"Y_CODE":38.385242,"KCODE1":"0100-00"}},
{"type":"Feature","geometry":null,"properties":{"KEY_CODE":"063240110","PREF":"06","CITY":"324","S_AREA":"011000","PREF_NAME":"山形県","CITY_NAME":"大江町","S_NAME":"大字小釿","KIGO_E":"","HCODE":8101,"AREA":3082256.744,"PERIMETER":9139.749,"R2KAxx":3390,"R2KAxx_ID":3389,"KIHON1":"0110","DUMMY1":"-","KIHON2":"00","KEYCODE1":"324011000","KEYCODE2":"3240110","AREA_MAX_F":"M","KIGO_D":"","N_KEN":"","N_CITY":"","KIGO_I":"","KBSUM":1,"JINKO":28,"SETAI":11,"X_CODE":140.141537,"Y_CODE":38.39693,"KCODE1":"0110-00"}},
{"type":"Feature","geometry":null,"properties":{"KEY_CODE":"063240120","PREF":"06","CITY":"324","S_AREA":"012000","PREF_NAME":"山形県","CITY_NAME":"大江町","S_NAME":"大字橋上","KIGO_E":"","HCODE":8101,"AREA":1104620.994,"PERIMETER":4694.915,"R2KAxx":3391,"R2KAxx_ID":3390,"KIHON1":"0120","DUMMY1":"-","KIHON2":"00","KEYCODE1":"324012000","KEYCODE2":"3240120","AREA_MAX_F":"M","KIGO_D":"","N_KEN":"","N_CITY":"","KIGO_I":"","KBSUM":1,"JINKO":56,"SETAI":19,"X_CODE":140.1375,"Y_CODE":38.378265,"KCODE1":"0120-00"}},
{"type":"Feature","geometry":null,"properties":{"KEY_CODE":"063240130","PREF":"06","CITY":"324","S_AREA":"013000","PREF_NAME":"山形県","CITY_NAME":"大江町","S_NAME":"大字材木","KIGO_E":"","HCODE":8101,"AREA":792693.891,"PERIMETER":3990.376,"R2KAxx":3392,"R2KAxx_ID":3391,"KIHON1":"0130","DUMMY1":"-","KIHON2":"00","KEYCODE1":"324013000","KEYCODE2":"3240130","AREA_MAX_F":"M","KIGO_D":"","N_KEN":"","N_CITY":"","KIGO_I":"","KBSUM":1,"JINKO":14,"SETAI":6,"X_CODE":140.143359,"Y_CODE":38.370623,"KCODE1":"0130-00"}},
{"type":"Feature","geometry":null,"properties":{"KEY_CODE":"063240140","PREF":"06","CITY":"324","S_AREA":"014000","PREF_NAME":"山形県","CITY_NAME":"大江町","S_NAME":"大字顔好甲","KIGO_E":"","HCODE":8101,"AREA":2867216.064,"PERIMETER":8531.182,"R2KAxx":3393,"R2KAxx_ID":3392,"KIHON1":"0140","DUMMY1":"-","KIHON2":"00","KEYCODE1":"324014000","KEYCODE2":"3240140","AREA_MAX_F":"M","KIGO_D":"","N_KEN":"","N_CITY":"","KIGO_I":"","KBSUM":4,"JINKO":176,"SETAI":67,"X_CODE":140.151429,"Y_CODE":38.381374,"KCODE1":"0140-00"}},
{"type":"Feature","geometry":null,"properties":{"KEY_CODE":"063240150","PREF":"06","CITY":"324","S_AREA":"015000","PREF_NAME":"山形県","CITY_NAME":"大江町","S_NAME":"大字本郷甲","KIGO_E":"","HCODE":8101,"AREA":2332560.738,"PERIMETER":8014.813,"R2KAxx":3394,"R2KAxx_ID":3393,"KIHON1":"0150","DUMMY1":"-","KIHON2":"00","KEYCODE1":"324015000","KEYCODE2":"3240150","AREA_MAX_F":"M","KIGO_D":"","N_KEN":"","N_CITY":"","KIGO_I":"","KBSUM":1,"JINKO":36,"SETAI":12,"X_CODE":140.159983,"Y_CODE":38.39186,"KCODE1":"0150-00"}},
{"type":"Feature","geometry":null,"properties":{"KEY_CODE":"063240160","PREF":"06","CITY":"324","S_AREA":"016000","PREF_NAME":"山形県","CITY_NAME":"大江町","S_NAME":"大字本郷丙","KIGO_E":"","HCODE":8101,"AREA":4737579.78,"PERIMETER":12835.789,"R2KAxx":3395,"R2KAxx_ID":3394,"KIHON1":"0160","DUMMY1":"-","KIHON2":"00","KEYCODE1":"324016000","KEYCODE2":"3240160","AREA_MAX_F":"M","KIGO_D":"","N_KEN":"","N_CITY":"","KIGO_I":"","KBSUM":8,"JINKO":851,"SETAI":263,"X_CODE":140.176614,"Y_CODE":38.383416,"KCODE1":"0160-00"}},
{"type":"Feature","geometry":null,"properties":{"KEY_CODE":"063240170","PREF":"06","CITY":"324","S_AREA":"017000","PREF_NAME":"山形県","CITY_NAME":"大江町","S_NAME":"大字本郷戊","KIGO_E":"","HCODE":8101,"AREA":1956885.348,"PERIMETER":8296.715,"R2KAxx":3396,"R2KAxx_ID":3395,"KIHON1":"0170","DUMMY1":"-","KIHON2":"00","KEYCODE1":"324017000","KEYCODE2":"3240170","AREA_MAX_F":"M","KIGO_D":"","N_KEN":"","N_CITY":"","KIGO_I":"","KBSUM":2,"JINKO":123,"SETAI":42,"X_CODE":140.187568,"Y_CODE":38.38975,"KCODE1":"0170-00"}},
{"type":"Feature","geometry":null,"properties":{"KEY_CODE":"063240180","PREF":"06","CITY":"324","S_AREA":"018000","PREF_NAME":"山形県","CITY_NAME":"大江町","S_NAME":"大字本郷丁","KIGO_E":"","HCODE":8101,"AREA":851107.362,"PERIMETER":6709.872,"R2KAxx":3397,"R2KAxx_ID":3396,"KIHON1":"0180","DUMMY1":"-","KIHON2":"00","KEYCODE1":"324018000","KEYCODE2":"3240180","AREA_MAX_F":"M","KIGO_D":"","N_KEN":"","N_CITY":"","KIGO_I":"","KBSUM":5,"JINKO":482,"SETAI":142,"X_CODE":140.187926,"Y_CODE":38.381389,"KCODE1":"0180-00"}},
{"type":"Feature","geometry":null,"properties":{"KEY_CODE":"063240190","PREF":"06","CITY":"324","S_AREA":"019000","PREF_NAME":"山形県","CITY_NAME":"大江町","S_NAME":"大字本郷己","KIGO_E":"","HCODE":8101,"AREA":389843.125,"PERIMETER":3213.339,"R2KAxx":3398,"R2KAxx_ID":3397,"KIHON1":"0190","DUMMY1":"-","KIHON2":"00","KEYCODE1":"324019000","KEYCODE2":"3240190","AREA_MAX_F":"M","KIGO_D":"","N_KEN":"","N_CITY":"","KIGO_I":"","KBSUM":3,"JINKO":223,"SETAI":70,"X_CODE":140.198689,"Y_CODE":38.37553,"KCODE1":"0190-00"}},
{"type":"Feature","geometry":null,"properties":{"KEY_CODE":"063240200","PREF":"06","CITY":"324","S_AREA":"020000","PREF_NAME":"山形県","CITY_NAME":"大江町","S_NAME":"大字荻野","KIGO_E":"","HCODE":8101,"AREA":539693.497,"PERIMETER":3270.514,"R2KAxx":3399,"R2KAxx_ID":3398,"KIHON1":"0200","DUMMY1":"-","KIHON2":"00","KEYCODE1":"324020000","KEYCODE2":"3240200","AREA_MAX_F":"M","KIGO_D":"","N_KEN":"","N_CITY":"","KIGO_I":"","KBSUM":2,"JINKO":87,"SETAI":29,"X_CODE":140.181639,"Y_CODE":38.368887,"KCODE1":"0200-00"}},
{"type":"Feature","geometry":null,"properties":{"KEY_CODE":"063240210","PREF":"06","CITY":"324","S_AREA":"021000","PREF_NAME":"山形県","CITY_NAME":"大江町","S_NAME":"大字堂屋敷","KIGO_E":"","HCODE":8101,"AREA":2131263.986,"PERIMETER":8134.683,"R2KAxx":3400,"R2KAxx_ID":3399,"KIHON1":"0210","DUMMY1":"-","KIHON2":"00","KEYCODE1":"324021000","KEYCODE2":"3240210","AREA_MAX_F":"M","KIGO_D":"","N_KEN":"","N_CITY":"","KIGO_I":"","KBSUM":1,"JINKO":88,"SETAI":25,"X_CODE":140.171974,"Y_CODE":38.36303,"KCODE1":"0210-00"}},
{"type":"Feature","geometry":null,"properties":{"KEY_CODE":"063240220","PREF":"06","CITY":"324","S_AREA":"022000","PREF_NAME":"山形県","CITY_NAME":"大江町","S_NAME":"大字本郷乙","KIGO_E":"","HCODE":8101,"AREA":545941.446,"PERIMETER":3475.267,"R2KAxx":3401,"R2KAxx_ID":3400,"KIHON1":"0220","DUMMY1":"-","KIHON2":"00","KEYCODE1":"324022000","KEYCODE2":"3240220","AREA_MAX_F":"M","KIGO_D":"","N_KEN":"","N_CITY":"","KIGO_I":"","KBSUM":1,"JINKO":18,"SETAI":6,"X_CODE":140.166478,"Y_CODE":38.378974,"KCODE1":"0220-00"}},
{"type":"Feature","geometry":null,"properties":{"KEY_CODE":"063240230","PREF":"06","CITY":"324","S_AREA":"023000","PREF_NAME":"山形県","CITY_NAME":"大江町","S_NAME":"大字塩ノ平","KIGO_E":"","HCODE":8101,"AREA":1266933.725,"PERIMETER":5576.655,"R2KAxx":3402,"R2KAxx_ID":3401,"KIHON1":"0230","DUMMY1":"-","KIHON2":"00","KEYCODE1":"324023000","KEYCODE2":"3240230","AREA_MAX_F":"M","KIGO_D":"","N_KEN":"","N_CITY":"","KIGO_I":"","KBSUM":1,"JINKO":60,"SETAI":15,"X_CODE":140.161374,"Y_CODE":38.367742,"KCODE1":"0230-00"}},
{"type":"Feature","geometry":null,"properties":{"KEY_CODE":"063240240","PREF":"06","CITY":"324","S_AREA":"024000","PREF_NAME":"山形県","CITY_NAME":"大江町","S_NAME":"大字所部","KIGO_E":"","HCODE":8101,"AREA":8354080.096,"PERIMETER":15323.689,"R2KAxx":3403,"R2KAxx_ID":3402,"KIHON1":"0240","DUMMY1":"-","KIHON2":"00","KEYCODE1":"324024000","KEYCODE2":"3240240","AREA_MAX_F":"M","KIGO_D":"","N_KEN":"","N_CITY":"","KIGO_I":"","KBSUM":1,"JINKO":15,"SETAI":6,"X_CODE":140.128031,"Y_CODE":38.363637,"KCODE1":"0240-00"}},
{"type":"Feature","geometry":null,"properties":{"KEY_CODE":"063240250","PREF":"06","CITY":"324","S_AREA":"025000","PREF_NAME":"山形県","CITY_NAME":"大江町","S_NAME":"大字柳川","KIGO_E":"","HCODE":8101,"AREA":18175815.333,"PERIMETER":22091.718,"R2KAxx":3404,"R2KAxx_ID":3403,"KIHON1":"0250","DUMMY1":"-","KIHON2":"00","KEYCODE1":"324025000","KEYCODE2":"3240250","AREA_MAX_F":"M","KIGO_D":"","N_KEN":"","N_CITY":"","KIGO_I":"","KBSUM":4,"JINKO":49,"SETAI":23,"X_CODE":140.035078,"Y_CODE":38.37749,"KCODE1":"0250-00"}},
{"type":"Feature","geometry":null,"properties":{"KEY_CODE":"063240260","PREF":"06","CITY":"324","S_AREA":"026000","PREF_NAME":"山形県","CITY_NAME":"大江町","S_NAME":"大字沢口","KIGO_E":"","HCODE":8101,"AREA":7761885.404,"PERIMETER":14195.22,"R2KAxx":3405,"R2KAxx_ID":3404,"KIHON1":"0260","DUMMY1":"-","KIHON2":"00","KEYCODE1":"324026000","KEYCODE2":"3240260","AREA_MAX_F":"M","KIGO_D":"","N_KEN":"","N_CITY":"","KIGO_I":"","KBSUM":3,"JINKO":35,"SETAI":19,"X_CODE":140.06866,"Y_CODE":38.358978,"KCODE1":"0260-00"}},
{"type":"Feature","geometry":null,"properties":{"KEY_CODE":"063240270","PREF":"06","CITY":"324","S_AREA":"027000","PREF_NAME":"山形県","CITY_NAME":"大江町","S_NAME":"大字黒森","KIGO_E":"","HCODE":8101,"AREA":6480531.998,"PERIMETER":10512.286,"R2KAxx":3406,"R2KAxx_ID":3405,"KIHON1":"0270","DUMMY1":"-","KIHON2":"00","KEYCODE1":"324027000","KEYCODE2":"3240270","AREA_MAX_F":"M","KIGO_D":"","N_KEN":"","N_CITY":"","KIGO_I":"","KBSUM":1,"JINKO":13,"SETAI":7,"X_CODE":140.084522,"Y_CODE":38.391199,"KCODE1":"0270-00"}},
{"type":"Feature","geometry":null,"properties":{"KEY_CODE":"063240280","PREF":"06","CITY":"324","S_AREA":"028000","PREF_NAME":"山形県","CITY_NAME":"大江町","S_NAME":"大字貫見","KIGO_E":"E1","HCODE":8101,"AREA":4593580.15,"PERIMETER":10307.047,"R2KAxx":3408,"R2KAxx_ID":3407,"KIHON1":"0280","DUMMY1":"-","KIHON2":"00","KEYCODE1":"324028000","KEYCODE2":"3240280","AREA_MAX_F":"","KIGO_D":"","N_KEN":"","N_CITY":"","KIGO_I":"","KBSUM":5,"JINKO":93,"SETAI":39,"X_CODE":140.096697,"Y_CODE":38.368749,"KCODE1":"0280-00"}},
{"type":"Feature","geometry":null,"properties":{"KEY_CODE":"063240280","PREF":"06","CITY":"324","S_AREA":"028000","PREF_NAME":"山形県","CITY_NAME":"大江町","S_NAME":"大字貫見","KIGO_E":"E2","HCODE":8101,"AREA":48889858.219,"PERIMETER":45725.824,"R2KAxx":3407,"R2KAxx_ID":3406,"KIHON1":"0280","DUMMY1":"-","KIHON2":"00","KEYCODE1":"324028000","KEYCODE2":"3240280","AREA_MAX_F":"M","KIGO_D":"","N_KEN":"","N_CITY":"","KIGO_I":"","KBSUM":0,"JINKO":0,"SETAI":0,"X_CODE":140.01147,"Y_CODE":38.319145,"KCODE1":"0280-00"}},
{"type":"Feature","geometry":null,"properties":{"KEY_CODE":"063240290","PREF":"06","CITY":"324","S_AREA":"029000","PREF_NAME":"山形県","CITY_NAME":"大江町","S_NAME":"大字小清","KIGO_E":"","HCODE":8101,"AREA":9142808.852,"PERIMETER":13524.157,"R2KAxx":3409,"R2KAxx_ID":3408,"KIHON1":"0290","DUMMY1":"-","KIHON2":"00","KEYCODE1":"324029000","KEYCODE2":"3240290","AREA_MAX_F":"M","KIGO_D":"","N_KEN":"","N_CITY":"","KIGO_I":"","KBSUM":1,"JINKO":3,"SETAI":3,"X_CODE":140.087632,"Y_CODE":38.346044,"KCODE1":"0290-00"}},
{"type":"Feature","geometry":null,"properties":{"KEY_CODE":"063240300","PREF":"06","CITY":"324","S_AREA":"030000","PREF_NAME":"山形県","CITY_NAME":"大江町","S_NAME":"大字原田","KIGO_E":"","HCODE":8101,"AREA":115641.796,"PERIMETER":1621.665,"R2KAxx":3410,"R2KAxx_ID":3409,"KIHON1":"0300","DUMMY1":"-","KIHON2":"00","KEYCODE1":"324030000","KEYCODE2":"3240300","AREA_MAX_F":"M","KIGO_D":"","N_KEN":"","N_CITY":"","KIGO_I":"","KBSUM":4,"JINKO":328,"SETAI":113,"X_CODE":140.194587,"Y_CODE":38.380287,"KCODE1":"0300-00"}}
]}